liberty/__init__.py
liberty/scheduler/__init__.py
liberty/scheduler/main.py
liberty/scheduler/airflow/__init__.py
liberty/scheduler/airflow/config/__init__.py
liberty/scheduler/airflow/config/connections.json
liberty/scheduler/airflow/config/variables.json
liberty/scheduler/airflow/drivers/__init__.py
liberty/scheduler/airflow/drivers/log4j2.properties
liberty/scheduler/airflow/drivers/ojdbc11.jar
liberty/scheduler/airflow/drivers/postgresql-42.7.4.jar
liberty/scheduler/airflow/manager/__init__.py
liberty/scheduler/airflow/manager/install.py
liberty/scheduler/airflow/manager/start.py
liberty/scheduler/airflow/manager/stop.py
liberty/scheduler/controllers/__init__.py
liberty/scheduler/controllers/airflow_controller.py
liberty/scheduler/dags/__init__.py
liberty/scheduler/dags/airflow-schedule.py
liberty/scheduler/postgres/__init__.py
liberty/scheduler/postgres/dump/__init__.py
liberty/scheduler/postgres/dump/liberty.dump
liberty/scheduler/postgres/dump/libnarf.dump
liberty/scheduler/postgres/dump/nomaarf.dump
liberty/scheduler/public/__init__.py
liberty/scheduler/public/frontend/index.html
liberty/scheduler/public/frontend/assets/background_ly-VdfFMP8a.jpg
liberty/scheduler/public/frontend/assets/index-Dcn6J_GQ.js
liberty/scheduler/public/frontend/assets/index-Dcn6J_GQ.js.map
liberty/scheduler/public/frontend/assets/index.es-D6oC0jBA-BuDo8Ufb.js
liberty/scheduler/public/frontend/assets/index.es-D6oC0jBA-BuDo8Ufb.js.map
liberty/scheduler/public/frontend/assets/logo_ly-HGj2PB94.svg
liberty/scheduler/public/frontend/assets/purify.es-BGDLgQxM-VhQmH9Os.js
liberty/scheduler/public/frontend/assets/purify.es-BGDLgQxM-VhQmH9Os.js.map
liberty/scheduler/public/offline/index.html
liberty/scheduler/public/offline/assets/logo_ly.png
liberty/scheduler/routes/__init__.py
liberty/scheduler/routes/airflow_routes.py
liberty/scheduler/routes/react_routes.py
liberty/scheduler/services/__init__.py
liberty/scheduler/services/airflow_services.py
liberty/scheduler/services/api_services.py
liberty_airflow-1.0.20.dist-info/licenses/LICENSE
liberty_airflow-1.0.20.dist-info/METADATA
liberty_airflow-1.0.20.dist-info/WHEEL
liberty_airflow-1.0.20.dist-info/entry_points.txt
liberty_airflow-1.0.20.dist-info/top_level.txt
liberty_airflow-1.0.20.dist-info/RECORD
