Metadata-Version: 2.4
Name: liberty-airflow
Version: 1.0.20
Summary: Liberty Airflow
Author: Franck Blettner
Author-email: franck.blettner@nomana-it.fr
Classifier: Programming Language :: Python :: 3
Classifier: Framework :: FastAPI
Classifier: Operating System :: OS Independent
Requires-Python: >=3.12
License-File: LICENSE
Requires-Dist: build==1.2.2.post1
Requires-Dist: dotenv==0.9.9
Requires-Dist: packaging==24.2
Requires-Dist: psycopg2-binary==2.9.10
Requires-Dist: pyproject_hooks==1.2.0
Requires-Dist: python-dotenv==1.0.1
Requires-Dist: setuptools==75.8.0
Requires-Dist: pyspark==3.5.3
Requires-Dist: fastapi==0.115.7
Requires-Dist: fastapi-socketio==0.0.10
Requires-Dist: uvicorn==0.34.0
Requires-Dist: greenlet==3.1.1
Requires-Dist: liberty-framework>=6.0.0
Requires-Dist: requests
Requires-Dist: werkzeug
Dynamic: author
Dynamic: author-email
Dynamic: classifier
Dynamic: description
Dynamic: description-content-type
Dynamic: license-file
Dynamic: requires-dist
Dynamic: requires-python
Dynamic: summary
